{"train/learning_rate": 0.0001, "train/entropy_loss": -1.096223348379135, "train/policy_gradient_loss": -0.002901747717987746, "train/value_loss": 63.160574722290036, "train/approx_kl": 0.0015467049088329077, "train/clip_fraction": 0.0, "train/loss": 26.8660888671875, "train/explained_variance": -0.0008745193481445312, "train/n_updates": 30, "train/clip_range": 0.2, "time/iterations": 4, "rollout/ep_rew_mean": -18.236363636363638, "rollout/ep_len_mean": 18.363636363636363, "time/fps": 903, "time/time_elapsed": 1, "time/total_timesteps": 1024}
{"train/learning_rate": 0.0001, "train/entropy_loss": -0.9948706738650799, "train/policy_gradient_loss": -0.015540071413852274, "train/value_loss": 57.908753633499146, "train/approx_kl": 0.009192959405481815, "train/clip_fraction": 0.044921875, "train/loss": 36.3919563293457, "train/explained_variance": -0.00010001659393310547, "train/n_updates": 50, "train/clip_range": 0.2, "time/iterations": 8, "rollout/ep_rew_mean": -14.33, "rollout/ep_len_mean": 14.77, "time/fps": 935, "time/time_elapsed": 2, "time/total_timesteps": 2048}
{"train/learning_rate": 0.0001, "train/entropy_loss": -0.4848888375257191, "train/policy_gradient_loss": -0.028683384525050457, "train/value_loss": 35.85419341137535, "train/approx_kl": 0.011471742764115334, "train/clip_fraction": 0.11430921052631579, "train/loss": 15.20870304107666, "train/explained_variance": 0.000992417335510254, "train/n_updates": 66, "train/clip_range": 0.2, "time/iterations": 12, "rollout/ep_rew_mean": -4.05, "rollout/ep_len_mean": 5.05, "time/fps": 1049, "time/time_elapsed": 2, "time/total_timesteps": 3072}
{"train/learning_rate": 0.0001, "train/entropy_loss": -0.13198010390624404, "train/policy_gradient_loss": -0.011979097314178944, "train/value_loss": 1.0541081596165895, "train/approx_kl": 0.002760166535153985, "train/clip_fraction": 0.02734375, "train/loss": 0.16804289817810059, "train/explained_variance": 0.4814063310623169, "train/n_updates": 100, "train/clip_range": 0.2, "time/iterations": 16, "rollout/ep_rew_mean": -3.12, "rollout/ep_len_mean": 4.12, "time/fps": 1044, "time/time_elapsed": 3, "time/total_timesteps": 4096}
{"train/learning_rate": 0.0001, "train/entropy_loss": -0.05069046206772328, "train/policy_gradient_loss": -0.0015278024860890583, "train/value_loss": 0.05290356435871217, "train/approx_kl": 0.00013136747293174267, "train/clip_fraction": 0.001171875, "train/loss": 0.07684433460235596, "train/explained_variance": 0.9587483927607536, "train/n_updates": 140, "train/clip_range": 0.2, "time/iterations": 20, "rollout/ep_rew_mean": -2.71, "rollout/ep_len_mean": 3.71, "time/fps": 1013, "time/time_elapsed": 5, "time/total_timesteps": 5120}
{"train/learning_rate": 0.0001, "train/entropy_loss": -0.025454572890885173, "train/policy_gradient_loss": -0.0027768313651904465, "train/value_loss": 0.16859087394550443, "train/approx_kl": 0.00012205424718558788, "train/clip_fraction": 0.00234375, "train/loss": 0.004202870186418295, "train/explained_variance": 0.8898540511727333, "train/n_updates": 180, "train/clip_range": 0.2, "time/iterations": 24, "rollout/ep_rew_mean": -2.64, "rollout/ep_len_mean": 3.64, "time/fps": 1004, "time/time_elapsed": 6, "time/total_timesteps": 6144}
{"train/learning_rate": 0.0001, "train/entropy_loss": -0.020594177092425524, "train/policy_gradient_loss": -2.653687261044979e-08, "train/value_loss": 0.03742795561447565, "train/approx_kl": 0.0, "train/clip_fraction": 0.0, "train/loss": 0.003176075639203191, "train/explained_variance": 0.9712632857263088, "train/n_updates": 220, "train/clip_range": 0.2, "time/iterations": 28, "rollout/ep_rew_mean": -2.64, "rollout/ep_len_mean": 3.64, "time/fps": 1007, "time/time_elapsed": 7, "time/total_timesteps": 7168}
{"train/learning_rate": 0.0001, "train/entropy_loss": -0.010943228425458074, "train/policy_gradient_loss": -0.0025046732858754694, "train/value_loss": 0.15099609136814252, "train/approx_kl": 0.00012137903831899166, "train/clip_fraction": 0.00234375, "train/loss": 0.026059091091156006, "train/explained_variance": 0.9073437601327896, "train/n_updates": 260, "train/clip_range": 0.2, "time/iterations": 32, "rollout/ep_rew_mean": -2.77, "rollout/ep_len_mean": 3.77, "time/fps": 1005, "time/time_elapsed": 8, "time/total_timesteps": 8192}
{"train/learning_rate": 0.0001, "train/entropy_loss": -0.00840232806513086, "train/policy_gradient_loss": -3.952300176024437e-09, "train/value_loss": 0.028513744902375036, "train/approx_kl": 0.0, "train/clip_fraction": 0.0, "train/loss": 0.0015005674213171005, "train/explained_variance": 0.9780589137226343, "train/n_updates": 300, "train/clip_range": 0.2, "time/iterations": 36, "rollout/ep_rew_mean": -2.75, "rollout/ep_len_mean": 3.75, "time/fps": 1004, "time/time_elapsed": 9, "time/total_timesteps": 9216}
{"train/learning_rate": 0.0001, "train/entropy_loss": -0.008404902671463788, "train/policy_gradient_loss": -2.227461664006114e-08, "train/value_loss": 0.011967858703792444, "train/approx_kl": 0.0, "train/clip_fraction": 0.0, "train/loss": 0.0011329373810440302, "train/explained_variance": 0.9902317011728883, "train/n_updates": 340, "train/clip_range": 0.2, "time/iterations": 40, "rollout/ep_rew_mean": -2.64, "rollout/ep_len_mean": 3.64, "time/fps": 1002, "time/time_elapsed": 10, "time/total_timesteps": 10240}
{"train/learning_rate": 0.0001, "train/entropy_loss": -0.008402066316921263, "train/policy_gradient_loss": 4.42087184637785e-09, "train/value_loss": 0.007025310727658507, "train/approx_kl": 0.0, "train/clip_fraction": 0.0, "train/loss": 0.003881837008520961, "train/explained_variance": 0.9944646670483053, "train/n_updates": 380, "train/clip_range": 0.2, "time/iterations": 44, "rollout/ep_rew_mean": -2.65, "rollout/ep_len_mean": 3.65, "time/fps": 1003, "time/time_elapsed": 11, "time/total_timesteps": 11264}
{"train/learning_rate": 0.0001, "train/entropy_loss": -0.006682635546894744, "train/policy_gradient_loss": -9.200302883982658e-08, "train/value_loss": 0.006612065027366043, "train/approx_kl": 0.0, "train/clip_fraction": 0.0, "train/loss": 0.0021238005720078945, "train/explained_variance": 0.9923658315092325, "train/n_updates": 420, "train/clip_range": 0.2, "time/iterations": 48, "rollout/ep_rew_mean": -2.72, "rollout/ep_len_mean": 3.72, "time/fps": 1001, "time/time_elapsed": 12, "time/total_timesteps": 12288}
{"train/learning_rate": 0.0001, "train/entropy_loss": -0.0066862513136584315, "train/policy_gradient_loss": -4.970934242010117e-09, "train/value_loss": 0.0009822167556194472, "train/approx_kl": 0.0, "train/clip_fraction": 0.0, "train/loss": 0.00034312301431782544, "train/explained_variance": 0.9992007736582309, "train/n_updates": 460, "train/clip_range": 0.2, "time/iterations": 52, "rollout/ep_rew_mean": -2.84, "rollout/ep_len_mean": 3.84, "time/fps": 1003, "time/time_elapsed": 13, "time/total_timesteps": 13312}
{"train/learning_rate": 0.0001, "train/entropy_loss": -0.005195400130469352, "train/policy_gradient_loss": 6.586778908967971e-08, "train/value_loss": 0.0009733158534800168, "train/approx_kl": 0.0, "train/clip_fraction": 0.0, "train/loss": 7.371897663688287e-05, "train/explained_variance": 0.9973174519836903, "train/n_updates": 500, "train/clip_range": 0.2, "time/iterations": 56, "rollout/ep_rew_mean": -2.8, "rollout/ep_len_mean": 3.8, "time/fps": 994, "time/time_elapsed": 14, "time/total_timesteps": 14336}
{"train/learning_rate": 0.0001, "train/entropy_loss": -0.004048581415554508, "train/policy_gradient_loss": -4.7570210881531235e-09, "train/value_loss": 0.00015012278668677937, "train/approx_kl": 0.0, "train/clip_fraction": 0.0, "train/loss": 0.0001398605527356267, "train/explained_variance": 0.9998505939292954, "train/n_updates": 540, "train/clip_range": 0.2, "time/iterations": 60, "rollout/ep_rew_mean": -2.88, "rollout/ep_len_mean": 3.88, "time/fps": 996, "time/time_elapsed": 15, "time/total_timesteps": 15360}
{"train/learning_rate": 0.0001, "train/entropy_loss": -0.004050004691816866, "train/policy_gradient_loss": -6.394111551344394e-09, "train/value_loss": 7.147234821900384e-05, "train/approx_kl": 0.0, "train/clip_fraction": 0.0, "train/loss": 3.7189114664215595e-05, "train/explained_variance": 0.9999420234635181, "train/n_updates": 580, "train/clip_range": 0.2, "time/iterations": 64, "rollout/ep_rew_mean": -2.66, "rollout/ep_len_mean": 3.66, "time/fps": 995, "time/time_elapsed": 16, "time/total_timesteps": 16384}
{"train/learning_rate": 0.0001, "train/entropy_loss": -0.0040502897696569565, "train/policy_gradient_loss": -2.4141627363860607e-08, "train/value_loss": 2.5758615830540066e-05, "train/approx_kl": 0.0, "train/clip_fraction": 0.0, "train/loss": 3.4757424600684317e-06, "train/explained_variance": 0.9999803872542543, "train/n_updates": 620, "train/clip_range": 0.2, "time/iterations": 68, "rollout/ep_rew_mean": -2.71, "rollout/ep_len_mean": 3.71, "time/fps": 997, "time/time_elapsed": 17, "time/total_timesteps": 17408}
{"train/learning_rate": 0.0001, "train/entropy_loss": -0.005298218788811937, "train/policy_gradient_loss": 3.582972567528486e-08, "train/value_loss": 2.5344334291688142e-05, "train/approx_kl": 0.0, "train/clip_fraction": 0.0, "train/loss": 1.7845441107056104e-05, "train/explained_variance": 0.9999783440762258, "train/n_updates": 660, "train/clip_range": 0.2, "time/iterations": 72, "rollout/ep_rew_mean": -2.83, "rollout/ep_len_mean": 3.83, "time/fps": 997, "time/time_elapsed": 18, "time/total_timesteps": 18432}
{"train/learning_rate": 0.0001, "train/entropy_loss": -0.005299970565829426, "train/policy_gradient_loss": -5.63828507438302e-08, "train/value_loss": 7.055530101851559e-06, "train/approx_kl": 0.0, "train/clip_fraction": 0.0, "train/loss": 2.2027875274943653e-06, "train/explained_variance": 0.9999944140831758, "train/n_updates": 700, "train/clip_range": 0.2, "time/iterations": 76, "rollout/ep_rew_mean": -2.85, "rollout/ep_len_mean": 3.85, "time/fps": 996, "time/time_elapsed": 19, "time/total_timesteps": 19456}
{"train/learning_rate": 0.0001, "train/entropy_loss": -0.004276499984553084, "train/policy_gradient_loss": -0.003653441241476685, "train/value_loss": 0.13567337630447582, "train/approx_kl": 0.0003478142898529768, "train/clip_fraction": 0.003125, "train/loss": 0.00405347254127264, "train/explained_variance": 0.9180237874388695, "train/n_updates": 740, "train/clip_range": 0.2, "time/iterations": 80, "rollout/ep_rew_mean": -2.61, "rollout/ep_len_mean": 3.61, "time/fps": 995, "time/time_elapsed": 20, "time/total_timesteps": 20480}
{"train/learning_rate": 0.0001, "train/entropy_loss": -0.004013600939651951, "train/policy_gradient_loss": -2.110318746417761e-08, "train/value_loss": 1.5151448675965184e-05, "train/approx_kl": 0.0, "train/clip_fraction": 0.0, "train/loss": 3.6167473353998503e-06, "train/explained_variance": 0.9999871941063248, "train/n_updates": 780, "train/clip_range": 0.2, "time/iterations": 84, "rollout/ep_rew_mean": -2.64, "rollout/ep_len_mean": 3.64, "time/fps": 997, "time/time_elapsed": 21, "time/total_timesteps": 21504}
{"train/learning_rate": 0.0001, "train/entropy_loss": -0.004020903562195599, "train/policy_gradient_loss": -2.1015875972807408e-08, "train/value_loss": 4.766999779448611e-06, "train/approx_kl": 0.0, "train/clip_fraction": 0.0, "train/loss": 4.5793785830028355e-06, "train/explained_variance": 0.9999959067513373, "train/n_updates": 820, "train/clip_range": 0.2, "time/iterations": 88, "rollout/ep_rew_mean": -2.59, "rollout/ep_len_mean": 3.59, "time/fps": 987, "time/time_elapsed": 22, "time/total_timesteps": 22528}
{"train/learning_rate": 0.0001, "train/entropy_loss": -0.003001235262490809, "train/policy_gradient_loss": -5.937181413173675e-10, "train/value_loss": 4.744789570843011e-06, "train/approx_kl": 0.0, "train/clip_fraction": 0.0, "train/loss": 8.550504162485595e-07, "train/explained_variance": 0.9999954291747599, "train/n_updates": 860, "train/clip_range": 0.2, "time/iterations": 92, "rollout/ep_rew_mean": -2.79, "rollout/ep_len_mean": 3.79, "time/fps": 969, "time/time_elapsed": 24, "time/total_timesteps": 23552}
{"train/learning_rate": 0.0001, "train/entropy_loss": -0.0030028109904378653, "train/policy_gradient_loss": -3.292516339570284e-08, "train/value_loss": 7.729785615584462e-07, "train/approx_kl": 0.0, "train/clip_fraction": 0.0, "train/loss": -3.3794620435401157e-09, "train/explained_variance": 0.9999990967294821, "train/n_updates": 900, "train/clip_range": 0.2, "time/iterations": 96, "rollout/ep_rew_mean": -2.57, "rollout/ep_len_mean": 3.57, "time/fps": 969, "time/time_elapsed": 25, "time/total_timesteps": 24576}
{"train/learning_rate": 0.0001, "train/entropy_loss": -0.002281739431782626, "train/policy_gradient_loss": -7.683411240577698e-09, "train/value_loss": 2.0325600042170323e-06, "train/approx_kl": 0.0, "train/clip_fraction": 0.0, "train/loss": 1.4660091096629912e-07, "train/explained_variance": 0.9999969850116486, "train/n_updates": 940, "train/clip_range": 0.2, "time/iterations": 100, "rollout/ep_rew_mean": -2.68, "rollout/ep_len_mean": 3.68, "time/fps": 970, "time/time_elapsed": 26, "time/total_timesteps": 25600}
{"train/learning_rate": 0.0001, "train/entropy_loss": -0.0022815138450823723, "train/policy_gradient_loss": 3.2789102988317607e-09, "train/value_loss": 7.284246072103428e-07, "train/approx_kl": 0.0, "train/clip_fraction": 0.0, "train/loss": 4.751277629111428e-07, "train/explained_variance": 0.9999994886028958, "train/n_updates": 980, "train/clip_range": 0.2, "time/iterations": 104, "rollout/ep_rew_mean": -2.72, "rollout/ep_len_mean": 3.72, "time/fps": 972, "time/time_elapsed": 27, "time/total_timesteps": 26624}
{"train/learning_rate": 0.0001, "train/entropy_loss": -0.0022821555932750924, "train/policy_gradient_loss": -2.948218025267124e-09, "train/value_loss": 6.204339071835818e-07, "train/approx_kl": 0.0, "train/clip_fraction": 0.0, "train/loss": 5.799619771096332e-07, "train/explained_variance": 0.9999995175504637, "train/n_updates": 1020, "train/clip_range": 0.2, "time/iterations": 108, "rollout/ep_rew_mean": -2.66, "rollout/ep_len_mean": 3.66, "time/fps": 972, "time/time_elapsed": 28, "time/total_timesteps": 27648}
{"train/learning_rate": 0.0001, "train/entropy_loss": -0.002281704664346762, "train/policy_gradient_loss": -2.764863893389702e-10, "train/value_loss": 8.134953252358912e-07, "train/approx_kl": 0.0, "train/clip_fraction": 0.0, "train/loss": 3.3277774491580203e-07, "train/explained_variance": 0.999999444232742, "train/n_updates": 1060, "train/clip_range": 0.2, "time/iterations": 112, "rollout/ep_rew_mean": -2.57, "rollout/ep_len_mean": 3.57, "time/fps": 973, "time/time_elapsed": 29, "time/total_timesteps": 28672}
{"train/learning_rate": 0.0001, "train/entropy_loss": -0.002281970717012882, "train/policy_gradient_loss": 1.6530975699424743e-09, "train/value_loss": 9.30251600972376e-07, "train/approx_kl": 0.0, "train/clip_fraction": 0.0, "train/loss": 6.040858693268092e-07, "train/explained_variance": 0.9999991899855445, "train/n_updates": 1100, "train/clip_range": 0.2, "time/iterations": 116, "rollout/ep_rew_mean": -2.74, "rollout/ep_len_mean": 3.74, "time/fps": 971, "time/time_elapsed": 30, "time/total_timesteps": 29696}
{"train/learning_rate": 0.0001, "train/entropy_loss": -0.002280795745900832, "train/policy_gradient_loss": 7.898779585957526e-09, "train/value_loss": 6.466670824156751e-07, "train/approx_kl": 0.0, "train/clip_fraction": 0.0, "train/loss": 5.119643446960254e-07, "train/explained_variance": 0.9999994973235289, "train/n_updates": 1140, "train/clip_range": 0.2, "time/iterations": 120, "rollout/ep_rew_mean": -2.82, "rollout/ep_len_mean": 3.82, "time/fps": 973, "time/time_elapsed": 31, "time/total_timesteps": 30720}
{"train/learning_rate": 0.0001, "train/entropy_loss": -0.0022802912368206306, "train/policy_gradient_loss": -1.0477378964424133e-09, "train/value_loss": 6.084349018387058e-07, "train/approx_kl": 0.0, "train/clip_fraction": 0.0, "train/loss": 2.495982585060119e-07, "train/explained_variance": 0.999999595750495, "train/n_updates": 1180, "train/clip_range": 0.2, "time/iterations": 124, "rollout/ep_rew_mean": -2.64, "rollout/ep_len_mean": 3.64, "time/fps": 972, "time/time_elapsed": 32, "time/total_timesteps": 31744}
{"train/learning_rate": 0.0001, "train/entropy_loss": -0.0022799743339419363, "train/policy_gradient_loss": -2.2898893803358077e-08, "train/value_loss": 5.155555382607702e-07, "train/approx_kl": 0.0, "train/clip_fraction": 0.0, "train/loss": 3.097252374573145e-07, "train/explained_variance": 0.9999996989952535, "train/n_updates": 1220, "train/clip_range": 0.2, "time/iterations": 128, "rollout/ep_rew_mean": -2.45, "rollout/ep_len_mean": 3.45, "time/fps": 973, "time/time_elapsed": 33, "time/total_timesteps": 32768}
{"train/learning_rate": 0.0001, "train/entropy_loss": -0.0022797521349275486, "train/policy_gradient_loss": 3.486056812107563e-08, "train/value_loss": 6.173482457683121e-07, "train/approx_kl": 0.0, "train/clip_fraction": 0.0, "train/loss": 3.8024407444936514e-07, "train/explained_variance": 0.9999996902707551, "train/n_updates": 1260, "train/clip_range": 0.2, "time/iterations": 132, "rollout/ep_rew_mean": -2.79, "rollout/ep_len_mean": 3.79, "time/fps": 973, "time/time_elapsed": 34, "time/total_timesteps": 33792}
{"train/learning_rate": 0.0001, "train/entropy_loss": -0.0022791379975387826, "train/policy_gradient_loss": -4.493631422519684e-09, "train/value_loss": 3.7148688201149584e-07, "train/approx_kl": 0.0, "train/clip_fraction": 0.0, "train/loss": 2.533617760036577e-07, "train/explained_variance": 0.9999996306320327, "train/n_updates": 1300, "train/clip_range": 0.2, "time/iterations": 136, "rollout/ep_rew_mean": -2.73, "rollout/ep_len_mean": 3.73, "time/fps": 974, "time/time_elapsed": 35, "time/total_timesteps": 34816}
{"train/learning_rate": 0.0001, "train/entropy_loss": -0.0022795210097683594, "train/policy_gradient_loss": -9.725044947117566e-09, "train/value_loss": 6.211208251727385e-07, "train/approx_kl": 0.0, "train/clip_fraction": 0.0, "train/loss": 3.483533816961426e-07, "train/explained_variance": 0.999999480538861, "train/n_updates": 1340, "train/clip_range": 0.2, "time/iterations": 140, "rollout/ep_rew_mean": -2.78, "rollout/ep_len_mean": 3.78, "time/fps": 974, "time/time_elapsed": 36, "time/total_timesteps": 35840}
{"train/learning_rate": 0.0001, "train/entropy_loss": -0.002278114762157202, "train/policy_gradient_loss": 4.6216882765293125e-09, "train/value_loss": 3.7987492154556436e-06, "train/approx_kl": 0.0, "train/clip_fraction": 0.0, "train/loss": 2.4391165425186045e-06, "train/explained_variance": 0.9999863413740968, "train/n_updates": 1380, "train/clip_range": 0.2, "time/iterations": 144, "rollout/ep_rew_mean": -2.71, "rollout/ep_len_mean": 3.71, "time/fps": 975, "time/time_elapsed": 37, "time/total_timesteps": 36864}
{"train/learning_rate": 0.0001, "train/entropy_loss": -0.0016932186495978384, "train/policy_gradient_loss": 6.668269634246826e-08, "train/value_loss": 0.0012254098785433598, "train/approx_kl": 0.0, "train/clip_fraction": 0.0, "train/loss": 9.196226164931431e-05, "train/explained_variance": 0.9967399521265179, "train/n_updates": 1420, "train/clip_range": 0.2, "time/iterations": 148, "rollout/ep_rew_mean": -2.83, "rollout/ep_len_mean": 3.83, "time/fps": 973, "time/time_elapsed": 38, "time/total_timesteps": 37888}
{"train/learning_rate": 0.0001, "train/entropy_loss": -0.0016927839737036266, "train/policy_gradient_loss": -1.4479155652225018e-09, "train/value_loss": 1.6838705234789587e-05, "train/approx_kl": 0.0, "train/clip_fraction": 0.0, "train/loss": 3.5479395137372194e-06, "train/explained_variance": 0.9999840117161511, "train/n_updates": 1460, "train/clip_range": 0.2, "time/iterations": 152, "rollout/ep_rew_mean": -2.53, "rollout/ep_len_mean": 3.53, "time/fps": 973, "time/time_elapsed": 39, "time/total_timesteps": 38912}
{"train/learning_rate": 0.0001, "train/entropy_loss": -0.0016933140403125435, "train/policy_gradient_loss": -1.1350493878126144e-10, "train/value_loss": 7.5523371311447814e-06, "train/approx_kl": 0.0, "train/clip_fraction": 0.0, "train/loss": 2.065364469672204e-06, "train/explained_variance": 0.9999941248838695, "train/n_updates": 1500, "train/clip_range": 0.2, "time/iterations": 156, "rollout/ep_rew_mean": -2.64, "rollout/ep_len_mean": 3.64, "time/fps": 973, "time/time_elapsed": 41, "time/total_timesteps": 39936}
{"train/learning_rate": 0.0001, "train/entropy_loss": -0.0016923551433137619, "train/policy_gradient_loss": -1.6763806343078614e-09, "train/value_loss": 4.111748607993348e-06, "train/approx_kl": 0.0, "train/clip_fraction": 0.0, "train/loss": 5.325046004145406e-06, "train/explained_variance": 0.9999971020229168, "train/n_updates": 1540, "train/clip_range": 0.2, "time/iterations": 160, "rollout/ep_rew_mean": -2.59, "rollout/ep_len_mean": 3.59, "time/fps": 973, "time/time_elapsed": 42, "time/total_timesteps": 40960}
{"train/learning_rate": 0.0001, "train/entropy_loss": -0.001692530336731579, "train/policy_gradient_loss": -2.0534207578748463e-08, "train/value_loss": 4.811284977179753e-06, "train/approx_kl": 0.0, "train/clip_fraction": 0.0, "train/loss": 1.683773689364898e-06, "train/explained_variance": 0.9999964722364894, "train/n_updates": 1580, "train/clip_range": 0.2, "time/iterations": 164, "rollout/ep_rew_mean": -2.74, "rollout/ep_len_mean": 3.74, "time/fps": 973, "time/time_elapsed": 43, "time/total_timesteps": 41984}
{"train/learning_rate": 0.0001, "train/entropy_loss": -0.001692090497817844, "train/policy_gradient_loss": 3.6030542105436324e-09, "train/value_loss": 1.0359847444352255e-06, "train/approx_kl": 0.0, "train/clip_fraction": 0.0, "train/loss": 1.422559279262714e-07, "train/explained_variance": 0.9999987657051861, "train/n_updates": 1620, "train/clip_range": 0.2, "time/iterations": 168, "rollout/ep_rew_mean": -2.71, "rollout/ep_len_mean": 3.71, "time/fps": 970, "time/time_elapsed": 44, "time/total_timesteps": 43008}
{"train/learning_rate": 0.0001, "train/entropy_loss": -0.0012392754841130226, "train/policy_gradient_loss": -0.0034810047771316023, "train/value_loss": 0.03658868763735086, "train/approx_kl": 0.0005838884972035885, "train/clip_fraction": 0.003125, "train/loss": 0.1000337302684784, "train/explained_variance": 0.9793097078800201, "train/n_updates": 1660, "train/clip_range": 0.2, "time/iterations": 172, "rollout/ep_rew_mean": -2.65, "rollout/ep_len_mean": 3.65, "time/fps": 971, "time/time_elapsed": 45, "time/total_timesteps": 44032}
{"train/learning_rate": 0.0001, "train/entropy_loss": -0.0011008942034095525, "train/policy_gradient_loss": -1.6152625903487206e-09, "train/value_loss": 1.0076042774365134e-06, "train/approx_kl": 0.0, "train/clip_fraction": 0.0, "train/loss": 4.419861738824693e-07, "train/explained_variance": 0.9999991587849308, "train/n_updates": 1700, "train/clip_range": 0.2, "time/iterations": 176, "rollout/ep_rew_mean": -2.79, "rollout/ep_len_mean": 3.79, "time/fps": 971, "time/time_elapsed": 46, "time/total_timesteps": 45056}
{"train/learning_rate": 0.0001, "train/entropy_loss": -0.0011009654321242125, "train/policy_gradient_loss": -6.609479896724224e-09, "train/value_loss": 9.234924826628799e-07, "train/approx_kl": 0.0, "train/clip_fraction": 0.0, "train/loss": 8.424586326327699e-07, "train/explained_variance": 0.9999992992795796, "train/n_updates": 1740, "train/clip_range": 0.2, "time/iterations": 180, "rollout/ep_rew_mean": -2.82, "rollout/ep_len_mean": 3.82, "time/fps": 972, "time/time_elapsed": 47, "time/total_timesteps": 46080}
{"train/learning_rate": 0.0001, "train/entropy_loss": -0.0011009492169250733, "train/policy_gradient_loss": 5.395850166678429e-09, "train/value_loss": 8.93270874380292e-07, "train/approx_kl": 0.0, "train/clip_fraction": 0.0, "train/loss": 7.695000903140681e-08, "train/explained_variance": 0.9999993474611415, "train/n_updates": 1780, "train/clip_range": 0.2, "time/iterations": 184, "rollout/ep_rew_mean": -2.64, "rollout/ep_len_mean": 3.64, "time/fps": 970, "time/time_elapsed": 48, "time/total_timesteps": 47104}
{"train/learning_rate": 0.0001, "train/entropy_loss": -0.0007635464542545378, "train/policy_gradient_loss": -1.9790604710578918e-10, "train/value_loss": 0.0003842883132165298, "train/approx_kl": 0.0, "train/clip_fraction": 0.0, "train/loss": 0.00014667981304228306, "train/explained_variance": 0.9989897466730326, "train/n_updates": 1820, "train/clip_range": 0.2, "time/iterations": 188, "rollout/ep_rew_mean": -2.83, "rollout/ep_len_mean": 3.83, "time/fps": 971, "time/time_elapsed": 49, "time/total_timesteps": 48128}
{"train/learning_rate": 0.0001, "train/entropy_loss": -0.0007636071881279349, "train/policy_gradient_loss": 4.810135578736663e-09, "train/value_loss": 1.4812673523323383e-06, "train/approx_kl": 0.0, "train/clip_fraction": 0.0, "train/loss": 1.2578124142237357e-07, "train/explained_variance": 0.9999985808368592, "train/n_updates": 1860, "train/clip_range": 0.2, "time/iterations": 192, "rollout/ep_rew_mean": -2.83, "rollout/ep_len_mean": 3.83, "time/fps": 971, "time/time_elapsed": 50, "time/total_timesteps": 49152}
{"train/learning_rate": 0.0001, "train/entropy_loss": -0.0007635981826751958, "train/policy_gradient_loss": -1.4028046280145646e-09, "train/value_loss": 3.143612332778822e-07, "train/approx_kl": 0.0, "train/clip_fraction": 0.0, "train/loss": -2.8392861395332147e-08, "train/explained_variance": 0.999999599987234, "train/n_updates": 1900, "train/clip_range": 0.2, "time/iterations": 196, "rollout/ep_rew_mean": -2.71, "rollout/ep_len_mean": 3.71, "time/fps": 968, "time/time_elapsed": 51, "time/total_timesteps": 50176}
